.gitignore
MANIFEST.in
README
README.md
code_linter.py
setup.py
pyspark_pandas/__init__.py
pyspark_pandas/dataframe_rdd.py
pyspark_pandas/errors.py
pyspark_pandas/examples.py
pyspark_pandas.egg-info/PKG-INFO
pyspark_pandas.egg-info/SOURCES.txt
pyspark_pandas.egg-info/dependency_links.txt
pyspark_pandas.egg-info/requires.txt
pyspark_pandas.egg-info/top_level.txt